cortex/__init__.py
cortex/config.py
cortex/factory.py
cortex/py.typed
cortex/registry.py
cortex/tokens.py
cortex/types.py
cortex/utils.py
cortex/blocks/__init__.py
cortex/blocks/adapter.py
cortex/blocks/base.py
cortex/blocks/passthrough.py
cortex/blocks/postup.py
cortex/blocks/postup_gated.py
cortex/blocks/preup.py
cortex/blocks/registry.py
cortex/blocks/column/__init__.py
cortex/blocks/column/auto.py
cortex/blocks/column/column.py
cortex/blocks/column/routers.py
cortex/cells/__init__.py
cortex/cells/agalite.py
cortex/cells/base.py
cortex/cells/conv.py
cortex/cells/lstm.py
cortex/cells/mlstm.py
cortex/cells/registry.py
cortex/cells/slstm.py
cortex/cells/xl.py
cortex/cells/core/__init__.py
cortex/cells/core/axon_cell.py
cortex/cells/core/axon_layer.py
cortex/kernels/cuda/__init__.py
cortex/kernels/cuda/agalite/__init__.py
cortex/kernels/cuda/agalite/discounted_sum_binding.cpp
cortex/kernels/cuda/agalite/discounted_sum_cuda.py
cortex/kernels/cuda/agalite/discounted_sum_kernels.cu
cortex/kernels/cuda/rtu/__init__.py
cortex/kernels/cuda/rtu/rtu_seq_allin.py
cortex/kernels/cuda/rtu/rtu_seq_allin_binding.cpp
cortex/kernels/cuda/rtu/rtu_seq_allin_kernels.cu
cortex/kernels/cuda/rtu/rtu_seq_full.py
cortex/kernels/cuda/rtu/rtu_seq_full_binding.cpp
cortex/kernels/cuda/rtu/rtu_seq_full_kernels.cu
cortex/kernels/cuda/rtu/rtu_stream_diag_cuda.py
cortex/kernels/cuda/rtu/rtu_stream_full_cuda.py
cortex/kernels/cuda/srht/srht_binding.cpp
cortex/kernels/cuda/srht/srht_cuda.py
cortex/kernels/cuda/srht/srht_kernels.cu
cortex/kernels/pytorch/__init__.py
cortex/kernels/pytorch/agalite.py
cortex/kernels/pytorch/conv1d.py
cortex/kernels/pytorch/lstm.py
cortex/kernels/pytorch/mlstm.py
cortex/kernels/pytorch/slstm.py
cortex/kernels/pytorch/srht.py
cortex/kernels/pytorch/txl.py
cortex/kernels/pytorch/rtu/__init__.py
cortex/kernels/pytorch/rtu/rtu_stream_diag.py
cortex/kernels/pytorch/rtu/rtu_stream_fullrank.py
cortex/kernels/triton/lstm.py
cortex/kernels/triton/conv1d/__init__.py
cortexcore-0.1.5.dist-info/METADATA
cortexcore-0.1.5.dist-info/WHEEL
cortexcore-0.1.5.dist-info/top_level.txt
cortexcore-0.1.5.dist-info/RECORD
