Metadata-Version: 2.4
Name: cortexcore
Version: 0.1.5
Summary: cortex is a modular library for building recurrent backbones and agent memory systems.
Author-email: Subhojeet Pramanik <email@subho.in>
License: MIT
Project-URL: Repository, https://github.com/Metta-AI/metta/tree/main/packages/cortex
Requires-Python: >=3.12
Requires-Dist: torch
Requires-Dist: pydantic>=2.11.5
Requires-Dist: tensordict
Requires-Dist: einops
Requires-Dist: ninja>=1.11.1
Requires-Dist: triton>=2.0.0; platform_system == "Linux"
